AIJIdevtools-1.4.4.dist-info/METADATA
AIJIdevtools-1.4.4.dist-info/RECORD
AIJIdevtools-1.4.4.dist-info/WHEEL
AIJIdevtools-1.4.4.dist-info/top_level.txt
devtools/__init__.py
devtools/cache.py
devtools/cli.py
devtools/daemon.py
devtools/dictools.py
devtools/exctools.py
devtools/file.py
devtools/listools.py
devtools/remotetools.py
devtools/sqltools.py
devtools/timed_cache.py
devtools/trantools.py
devtools/web.py
devtools/django/__init__.py
devtools/flask_converters/__init__.py
devtools/flask_errors/__init__.py
devtools/requests/__init__.py
devtools/requests/sessions.py
devtools/rest_framework/__init__.py
devtools/rest_framework/fields.py
