Metadata-Version: 2.1
Name: AIJIdevtools
Version: 1.4.4
Summary: Some useful helper-funcs for devpers
Home-page: https://github.com/AIJIJI/devtools
Author: AIJI
Author-email: thecrazyaiji@gmail.com
License: UNKNOWN
Platform: UNKNOWN
Classifier: Programming Language :: Python :: 3.7
Classifier: License :: OSI Approved :: MIT License
Classifier: Operating System :: POSIX :: Linux
Classifier: Development Status :: 1 - Planning
Requires-Dist: sh
Requires-Dist: sqlparse
Requires-Dist: termcolor
Requires-Dist: requests
